BCBio/__init__.py
BCBio/GFF/GFFOutput.py
BCBio/GFF/GFFParser.py
BCBio/GFF/__init__.py
BCBio/GFF/_utils.py
bcbio_gff-0.7.1.dist-info/LICENSE
bcbio_gff-0.7.1.dist-info/METADATA
bcbio_gff-0.7.1.dist-info/WHEEL
bcbio_gff-0.7.1.dist-info/top_level.txt
bcbio_gff-0.7.1.dist-info/RECORD
